{"title":{"0":"The Shawshank Redemption","1":"The Godfather","2":"The Dark Knight","3":"The Godfather Part II","4":"12 Angry Men","5":"Schindler's List","6":"The Lord of the Rings: The Return of the King","7":"Pulp Fiction","8":"The Lord of the Rings: The Fellowship of the Ring","9":"The Good, the Bad and the Ugly","10":"Forrest Gump","11":"Fight Club","12":"The Lord of the Rings: The Two Towers","13":"Inception","14":"Star Wars: Episode V - The Empire Strikes Back","15":"The Matrix","16":"Gandhi","17":"The Help","18":"The Iron Giant","19":"Aladdin","20":"Dersu Uzala","21":"Everything Everywhere All at Once","22":"Life of Brian","23":"The Sound of Music","24":"Persona","25":"It Happened One Night","26":"The Handmaiden","27":"The 400 Blows","28":"Cool Hand Luke","29":"Amores Perros","30":"Rebecca","31":"My Father and My Son","32":"The Grapes of Wrath","33":"Pirates of the Caribbean: The Curse of the Black Pearl","34":"Jai Bhim","35":"La haine","36":"Hachi: A Dog's Tale","37":"The Battle of Algiers","38":"To Be or Not to Be","39":"The Incredibles","40":"The Best Years of Our Lives","41":"The Exorcist","42":"Groundhog Day","43":"Before Sunset","44":"The Wizard of Oz","45":"Into the Wild","46":"Network","47":"Pather Panchali","48":"Rush","49":"Ratatouille","50":"Logan","51":"Stand by Me","52":"The Terminator","53":"Spotlight","54":"Platoon","55":"Rocky","56":"Ford v Ferrari","57":"Hotel Rwanda","58":"Tokyo Story","59":"The Passion of Joan of Arc","60":"Dead Poets Society","61":"Jaws","62":"The Big Lebowski","63":"Monsters, Inc.","64":"How to Train Your Dragon","65":"Mary and Max","66":"Room","67":"Mad Max: Fury Road","68":"The Seventh Seal","69":"Wild Tales","70":"Memories of Murder","71":"Mr. Smith Goes to Washington","72":"Sherlock Jr.","73":"Hacksaw Ridge","74":"The Wages of Fear","75":"Barry Lyndon","76":"Klaus","77":"In the Name of the Father","78":"The Deer Hunter","79":"The Grand Budapest Hotel","80":"The Third Man","81":"The General","82":"Gone Girl","83":"Wild Strawberries","84":"Ben-Hur","85":"Harry Potter and the Deathly Hallows: Part 2","86":"12 Years a Slave","87":"Before Sunrise","88":"On the Waterfront","89":"The Gold Rush","90":"Blade Runner","91":"Children of Heaven","92":"Million Dollar Baby","93":"Catch Me If You Can","94":"My Neighbor Totoro","95":"Prisoners","96":"Gran Torino","97":"Fargo","98":"Warrior","99":"Trainspotting","100":"Three Billboards Outside Ebbing, Missouri","101":"The Bridge on the River Kwai","102":"Howl's Moving Castle","103":"The Secret in Their Eyes","104":"Dial M for Murder","105":"Lock, Stock and Two Smoking Barrels","106":"Inside Out","107":"V for Vendetta","108":"Gone with the Wind","109":"Raging Bull","110":"Chinatown","111":"The Elephant Man","112":"The Thing","113":"Finding Nemo","114":"No Country for Old Men","115":"Kill Bill: Vol. 1","116":"Rashomon","117":"The Great Escape","118":"Jurassic Park","119":"The Treasure of the Sierra Madre","120":"Monty Python and the Holy Grail","121":"Spider-Man: No Way Home","122":"Yojimbo","123":"Shutter Island","124":"A Beautiful Mind","125":"The Sixth Sense","126":"The Truman Show","127":"There Will Be Blood","128":"Unforgiven","129":"Pan's Labyrinth","130":"Casino","131":"Ran","132":"Judgment at Nuremberg","133":"The Wolf of Wall Street","134":"Green Book","135":"All About Eve","136":"The Father","137":"Some Like It Hot","138":"The Kid","139":"Batman Begins","140":"Dangal","141":"For a Few Dollars More","142":"Downfall","143":"1917","144":"Like Stars on Earth","145":"Indiana Jones and the Last Crusade","146":"Bicycle Thieves","147":"Snatch","148":"Die Hard","149":"L.A. Confidential","150":"Metropolis","151":"A Separation","152":"Taxi Driver","153":"Heat","154":"Up","155":"Incendies","156":"The Sting","157":"To Kill a Mockingbird","158":"Scarface","159":"Hamilton","160":"Full Metal Jacket","161":"Double Indemnity","162":"Ikiru","163":"The Apartment","164":"A Clockwork Orange","165":"Am\u00c3\u00a9lie","166":"Vertigo","167":"North by Northwest","168":"Lawrence of Arabia","169":"M","170":"Citizen Kane","171":"Come and See","172":"The Hunt","173":"Reservoir Dogs","174":"Eternal Sunshine of the Spotless Mind","175":"2001: A Space Odyssey","176":"Capernaum","177":"Star Wars: Episode VI - Return of the Jedi","178":"High and Low","179":"Toy Story 3","180":"Singin' in the Rain","181":"3 Idiots","182":"Requiem for a Dream","183":"Top Gun: Maverick","184":"Your Name.","185":"Good Will Hunting","186":"Once Upon a Time in America","187":"Princess Mononoke","188":"Avengers: Endgame","189":"Braveheart","190":"Toy Story","191":"Coco","192":"Joker","193":"Inglourious Basterds","194":"Amadeus","195":"Oldboy","196":"The Dark Knight Rises","197":"Dr. Strangelove or: How I Learned to Stop Worrying and Love the Bomb","198":"American Beauty","199":"Spider-Man: Into the Spider-Verse","200":"Aliens","201":"Witness for the Prosecution","202":"Avengers: Infinity War","203":"The Great Dictator","204":"The Shining","205":"Paths of Glory","206":"Sunset Blvd.","207":"The Lives of Others","208":"WALL\u00c2\u00b7E","209":"Django Unchained","210":"Indiana Jones and the Raiders of the Lost Ark","211":"Memento","212":"Apocalypse Now","213":"City Lights","214":"Alien","215":"Cinema Paradiso","216":"Rear Window","217":"Once Upon a Time in the West","218":"Modern Times","219":"The Intouchables","220":"Grave of the Fireflies","221":"Harakiri","222":"Casablanca","223":"Whiplash","224":"The Prestige","225":"The Usual Suspects","226":"American History X","227":"The Departed","228":"Gladiator","229":"The Lion King","230":"L\u00c3\u00a9on: The Professional","231":"Parasite","232":"The Pianist","233":"Psycho","234":"Spirited Away","235":"Back to the Future","236":"Terminator 2: Judgment Day","237":"Star Wars: Episode IV - A New Hope","238":"The Green Mile","239":"Interstellar","240":"Life Is Beautiful","241":"Saving Private Ryan","242":"City of God","243":"The Silence of the Lambs","244":"It's a Wonderful Life","245":"Seven Samurai","246":"Se7en","247":"One Flew Over the Cuckoo's Nest","248":"Goodfellas"},"Score":{"0":9.3,"1":9.2,"2":9.0,"3":9.0,"4":9.0,"5":9.0,"6":9.0,"7":8.9,"8":8.8,"9":8.8,"10":8.8,"11":8.8,"12":8.8,"13":8.8,"14":8.7,"15":8.7,"16":8.1,"17":8.1,"18":8.1,"19":8.0,"20":8.2,"21":8.1,"22":8.0,"23":8.1,"24":8.1,"25":8.1,"26":8.1,"27":8.1,"28":8.1,"29":8.1,"30":8.1,"31":8.2,"32":8.1,"33":8.1,"34":8.9,"35":8.1,"36":8.1,"37":8.1,"38":8.2,"39":8.0,"40":8.1,"41":8.1,"42":8.1,"43":8.1,"44":8.1,"45":8.1,"46":8.1,"47":8.3,"48":8.1,"49":8.1,"50":8.1,"51":8.1,"52":8.1,"53":8.1,"54":8.1,"55":8.1,"56":8.1,"57":8.1,"58":8.2,"59":8.2,"60":8.1,"61":8.1,"62":8.1,"63":8.1,"64":8.1,"65":8.1,"66":8.1,"67":8.1,"68":8.1,"69":8.1,"70":8.1,"71":8.1,"72":8.2,"73":8.1,"74":8.2,"75":8.1,"76":8.1,"77":8.1,"78":8.1,"79":8.1,"80":8.1,"81":8.2,"82":8.1,"83":8.1,"84":8.1,"85":8.1,"86":8.1,"87":8.1,"88":8.1,"89":8.2,"90":8.1,"91":8.2,"92":8.1,"93":8.1,"94":8.1,"95":8.1,"96":8.1,"97":8.1,"98":8.2,"99":8.1,"100":8.1,"101":8.2,"102":8.2,"103":8.2,"104":8.2,"105":8.2,"106":8.2,"107":8.2,"108":8.2,"109":8.2,"110":8.2,"111":8.2,"112":8.2,"113":8.2,"114":8.2,"115":8.2,"116":8.2,"117":8.2,"118":8.2,"119":8.2,"120":8.2,"121":8.3,"122":8.2,"123":8.2,"124":8.2,"125":8.2,"126":8.2,"127":8.2,"128":8.2,"129":8.2,"130":8.2,"131":8.2,"132":8.3,"133":8.2,"134":8.2,"135":8.2,"136":8.2,"137":8.2,"138":8.3,"139":8.2,"140":8.3,"141":8.2,"142":8.2,"143":8.2,"144":8.4,"145":8.2,"146":8.3,"147":8.2,"148":8.2,"149":8.2,"150":8.3,"151":8.3,"152":8.2,"153":8.3,"154":8.3,"155":8.3,"156":8.3,"157":8.3,"158":8.3,"159":8.4,"160":8.3,"161":8.3,"162":8.3,"163":8.3,"164":8.3,"165":8.3,"166":8.3,"167":8.3,"168":8.3,"169":8.3,"170":8.3,"171":8.4,"172":8.3,"173":8.3,"174":8.3,"175":8.3,"176":8.4,"177":8.3,"178":8.4,"179":8.3,"180":8.3,"181":8.4,"182":8.3,"183":8.4,"184":8.4,"185":8.3,"186":8.3,"187":8.4,"188":8.4,"189":8.4,"190":8.3,"191":8.4,"192":8.4,"193":8.3,"194":8.4,"195":8.4,"196":8.4,"197":8.4,"198":8.4,"199":8.4,"200":8.4,"201":8.4,"202":8.4,"203":8.4,"204":8.4,"205":8.4,"206":8.4,"207":8.4,"208":8.4,"209":8.4,"210":8.4,"211":8.4,"212":8.5,"213":8.5,"214":8.5,"215":8.5,"216":8.5,"217":8.5,"218":8.5,"219":8.5,"220":8.5,"221":8.6,"222":8.5,"223":8.5,"224":8.5,"225":8.5,"226":8.5,"227":8.5,"228":8.5,"229":8.5,"230":8.5,"231":8.5,"232":8.5,"233":8.5,"234":8.6,"235":8.5,"236":8.6,"237":8.6,"238":8.6,"239":8.6,"240":8.6,"241":8.6,"242":8.6,"243":8.6,"244":8.6,"245":8.6,"246":8.6,"247":8.7,"248":8.7},"Genre":{"0":"Drama","1":"Crime,Drama","2":"Action,Crime,Drama","3":"Crime,Drama","4":"Crime,Drama","5":"Biography,Drama,History","6":"Action,Adventure,Drama","7":"Crime,Drama","8":"Action,Adventure,Drama","9":"Adventure,Western","10":"Drama,Romance","11":"Drama","12":"Action,Adventure,Drama","13":"Action,Adventure,Sci-Fi","14":"Action,Adventure,Fantasy","15":"Action,Sci-Fi","16":"Biography,Drama,History","17":"Drama","18":"Animation,Action,Adventure","19":"Animation,Adventure,Comedy","20":"Adventure,Biography,Drama","21":"Action,Adventure,Comedy","22":"Comedy","23":"Biography,Drama,Family","24":"Drama,Thriller","25":"Comedy,Romance","26":"Drama,Romance,Thriller","27":"Crime,Drama","28":"Crime,Drama","29":"Drama,Thriller","30":"Drama,Film-Noir,Mystery","31":"Drama,Family","32":"Drama","33":"Action,Adventure,Fantasy","34":"Crime,Drama,Mystery","35":"Crime,Drama","36":"Biography,Drama,Family","37":"Drama,War","38":"Comedy,Romance,War","39":"Animation,Action,Adventure","40":"Drama,Romance,War","41":"Horror","42":"Comedy,Drama,Fantasy","43":"Drama,Romance","44":"Adventure,Family,Fantasy","45":"Adventure,Biography,Drama","46":"Drama","47":"Drama","48":"Action,Biography,Drama","49":"Animation,Adventure,Comedy","50":"Action,Drama,Sci-Fi","51":"Adventure,Drama","52":"Action,Sci-Fi","53":"Biography,Crime,Drama","54":"Drama,War","55":"Drama,Sport","56":"Action,Biography,Drama","57":"Biography,Drama,History","58":"Drama","59":"Biography,Drama,History","60":"Comedy,Drama","61":"Adventure,Thriller","62":"Comedy,Crime","63":"Animation,Adventure,Comedy","64":"Animation,Action,Adventure","65":"Animation,Comedy,Drama","66":"Drama,Thriller","67":"Action,Adventure,Sci-Fi","68":"Drama,Fantasy","69":"Comedy,Drama,Thriller","70":"Crime,Drama,Mystery","71":"Comedy,Drama","72":"Action,Comedy,Romance","73":"Biography,Drama,History","74":"Adventure,Drama,Thriller","75":"Adventure,Drama,War","76":"Animation,Adventure,Comedy","77":"Biography,Crime,Drama","78":"Drama,War","79":"Adventure,Comedy,Crime","80":"Film-Noir,Mystery,Thriller","81":"Action,Adventure,Comedy","82":"Drama,Mystery,Thriller","83":"Drama,Romance","84":"Adventure,Drama","85":"Adventure,Family,Fantasy","86":"Biography,Drama,History","87":"Drama,Romance","88":"Crime,Drama,Thriller","89":"Adventure,Comedy,Drama","90":"Action,Drama,Sci-Fi","91":"Drama,Family,Sport","92":"Drama,Sport","93":"Biography,Crime,Drama","94":"Animation,Comedy,Family","95":"Crime,Drama,Mystery","96":"Drama","97":"Crime,Thriller","98":"Action,Drama,Sport","99":"Drama","100":"Comedy,Crime,Drama","101":"Adventure,Drama,War","102":"Animation,Adventure,Family","103":"Drama,Mystery,Romance","104":"Crime,Thriller","105":"Action,Comedy,Crime","106":"Animation,Adventure,Comedy","107":"Action,Drama,Sci-Fi","108":"Drama,Romance,War","109":"Biography,Drama,Sport","110":"Drama,Mystery,Thriller","111":"Biography,Drama","112":"Horror,Mystery,Sci-Fi","113":"Animation,Adventure,Comedy","114":"Crime,Drama,Thriller","115":"Action,Crime,Drama","116":"Crime,Drama,Mystery","117":"Adventure,Drama,History","118":"Action,Adventure,Sci-Fi","119":"Adventure,Drama,Western","120":"Adventure,Comedy,Fantasy","121":"Action,Adventure,Fantasy","122":"Action,Drama,Thriller","123":"Mystery,Thriller","124":"Biography,Drama","125":"Drama,Mystery,Thriller","126":"Comedy,Drama","127":"Drama","128":"Drama,Western","129":"Drama,Fantasy,War","130":"Crime,Drama","131":"Action,Drama,War","132":"Drama,War","133":"Biography,Comedy,Crime","134":"Biography,Comedy,Drama","135":"Drama","136":"Drama,Mystery","137":"Comedy,Music,Romance","138":"Comedy,Drama,Family","139":"Action,Crime,Drama","140":"Action,Biography,Drama","141":"Western","142":"Biography,Drama,History","143":"Action,Drama,War","144":"Drama,Family","145":"Action,Adventure","146":"Drama","147":"Comedy,Crime","148":"Action,Thriller","149":"Crime,Drama,Mystery","150":"Drama,Sci-Fi","151":"Drama","152":"Crime,Drama","153":"Action,Crime,Drama","154":"Animation,Adventure,Comedy","155":"Drama,Mystery","156":"Comedy,Crime,Drama","157":"Crime,Drama","158":"Crime,Drama","159":"Biography,Drama,History","160":"Drama,War","161":"Crime,Drama,Film-Noir","162":"Drama","163":"Comedy,Drama,Romance","164":"Crime,Sci-Fi","165":"Comedy,Romance","166":"Mystery,Romance,Thriller","167":"Action,Adventure,Mystery","168":"Adventure,Biography,Drama","169":"Crime,Mystery,Thriller","170":"Drama,Mystery","171":"Drama,Thriller,War","172":"Drama","173":"Crime,Thriller","174":"Drama,Romance,Sci-Fi","175":"Adventure,Sci-Fi","176":"Drama","177":"Action,Adventure,Fantasy","178":"Crime,Drama,Mystery","179":"Animation,Adventure,Comedy","180":"Comedy,Musical,Romance","181":"Comedy,Drama","182":"Drama","183":"Action,Drama","184":"Animation,Drama,Fantasy","185":"Drama,Romance","186":"Crime,Drama","187":"Animation,Action,Adventure","188":"Action,Adventure,Drama","189":"Biography,Drama,History","190":"Animation,Adventure,Comedy","191":"Animation,Adventure,Comedy","192":"Crime,Drama,Thriller","193":"Adventure,Drama,War","194":"Biography,Drama,Music","195":"Action,Drama,Mystery","196":"Action,Drama","197":"Comedy,War","198":"Drama","199":"Animation,Action,Adventure","200":"Action,Adventure,Sci-Fi","201":"Crime,Drama,Mystery","202":"Action,Adventure,Sci-Fi","203":"Comedy,Drama,War","204":"Drama,Horror","205":"Drama,War","206":"Drama,Film-Noir","207":"Drama,Mystery,Thriller","208":"Animation,Adventure,Family","209":"Drama,Western","210":"Action,Adventure","211":"Mystery,Thriller","212":"Drama,Mystery,War","213":"Comedy,Drama,Romance","214":"Horror,Sci-Fi","215":"Drama,Romance","216":"Mystery,Thriller","217":"Western","218":"Comedy,Drama,Romance","219":"Biography,Comedy,Drama","220":"Animation,Drama,War","221":"Action,Drama,Mystery","222":"Drama,Romance,War","223":"Drama,Music","224":"Drama,Mystery,Sci-Fi","225":"Crime,Drama,Mystery","226":"Crime,Drama","227":"Crime,Drama,Thriller","228":"Action,Adventure,Drama","229":"Animation,Adventure,Drama","230":"Action,Crime,Drama","231":"Drama,Thriller","232":"Biography,Drama,Music","233":"Horror,Mystery,Thriller","234":"Animation,Adventure,Family","235":"Adventure,Comedy,Sci-Fi","236":"Action,Sci-Fi","237":"Action,Adventure,Fantasy","238":"Crime,Drama,Fantasy","239":"Adventure,Drama,Sci-Fi","240":"Comedy,Drama,Romance","241":"Drama,War","242":"Crime,Drama","243":"Crime,Drama,Thriller","244":"Drama,Family,Fantasy","245":"Action,Drama","246":"Crime,Drama,Mystery","247":"Drama","248":"Biography,Crime,Drama"},"Date":{"0":1994,"1":1972,"2":2008,"3":1974,"4":1957,"5":1993,"6":2003,"7":1994,"8":2001,"9":1966,"10":1994,"11":1999,"12":2002,"13":2010,"14":1980,"15":1999,"16":1982,"17":2011,"18":1999,"19":1992,"20":1975,"21":2022,"22":1979,"23":1965,"24":1966,"25":1934,"26":2016,"27":1959,"28":1967,"29":2000,"30":1940,"31":2005,"32":1940,"33":2003,"34":2021,"35":1995,"36":2009,"37":1966,"38":1942,"39":2004,"40":1946,"41":1973,"42":1993,"43":2004,"44":1939,"45":2007,"46":1976,"47":1955,"48":2013,"49":2007,"50":2017,"51":1986,"52":1984,"53":2015,"54":1986,"55":1976,"56":2019,"57":2004,"58":1953,"59":1928,"60":1989,"61":1975,"62":1998,"63":2001,"64":2010,"65":2009,"66":2015,"67":2015,"68":1957,"69":2014,"70":2003,"71":1939,"72":1924,"73":2016,"74":1953,"75":1975,"76":2019,"77":1993,"78":1978,"79":2014,"80":1949,"81":1926,"82":2014,"83":1957,"84":1959,"85":2011,"86":2013,"87":1995,"88":1954,"89":1925,"90":1982,"91":1997,"92":2004,"93":2002,"94":1988,"95":2013,"96":2008,"97":1996,"98":2011,"99":1996,"100":2017,"101":1957,"102":2004,"103":2009,"104":1954,"105":1998,"106":2015,"107":2005,"108":1939,"109":1980,"110":1974,"111":1980,"112":1982,"113":2003,"114":2007,"115":2003,"116":1950,"117":1963,"118":1993,"119":1948,"120":1975,"121":2021,"122":1961,"123":2010,"124":2001,"125":1999,"126":1998,"127":2007,"128":1992,"129":2006,"130":1995,"131":1985,"132":1961,"133":2013,"134":2018,"135":1950,"136":2020,"137":1959,"138":1921,"139":2005,"140":2016,"141":1965,"142":2004,"143":2019,"144":2007,"145":1989,"146":1948,"147":2000,"148":1988,"149":1997,"150":1927,"151":2011,"152":1976,"153":1995,"154":2009,"155":2010,"156":1973,"157":1962,"158":1983,"159":2020,"160":1987,"161":1944,"162":1952,"163":1960,"164":1971,"165":2001,"166":1958,"167":1959,"168":1962,"169":1931,"170":1941,"171":1985,"172":2012,"173":1992,"174":2004,"175":1968,"176":2018,"177":1983,"178":1963,"179":2010,"180":1952,"181":2009,"182":2000,"183":2022,"184":2016,"185":1997,"186":1984,"187":1997,"188":2019,"189":1995,"190":1995,"191":2017,"192":2019,"193":2009,"194":1984,"195":2003,"196":2012,"197":1964,"198":1999,"199":2018,"200":1986,"201":1957,"202":2018,"203":1940,"204":1980,"205":1957,"206":1950,"207":2006,"208":2008,"209":2012,"210":1981,"211":2000,"212":1979,"213":1931,"214":1979,"215":1988,"216":1954,"217":1968,"218":1936,"219":2011,"220":1988,"221":1962,"222":1942,"223":2014,"224":2006,"225":1995,"226":1998,"227":2006,"228":2000,"229":1994,"230":1994,"231":2019,"232":2002,"233":1960,"234":2001,"235":1985,"236":1991,"237":1977,"238":1999,"239":2014,"240":1997,"241":1998,"242":2002,"243":1991,"244":1946,"245":1954,"246":1995,"247":1975,"248":1990},"duree":{"0":142,"1":175,"2":152,"3":202,"4":96,"5":195,"6":201,"7":154,"8":178,"9":178,"10":142,"11":139,"12":179,"13":148,"14":124,"15":136,"16":191,"17":146,"18":86,"19":90,"20":142,"21":139,"22":94,"23":172,"24":83,"25":105,"26":145,"27":99,"28":127,"29":154,"30":130,"31":112,"32":129,"33":143,"34":164,"35":98,"36":93,"37":121,"38":99,"39":115,"40":170,"41":122,"42":101,"43":80,"44":102,"45":148,"46":121,"47":125,"48":123,"49":111,"50":137,"51":89,"52":107,"53":129,"54":2,"55":2,"56":152,"57":121,"58":136,"59":114,"60":128,"61":124,"62":117,"63":92,"64":98,"65":92,"66":118,"67":2,"68":96,"69":122,"70":132,"71":129,"72":45,"73":139,"74":131,"75":185,"76":96,"77":133,"78":183,"79":99,"80":93,"81":67,"82":149,"83":91,"84":212,"85":130,"86":134,"87":101,"88":108,"89":95,"90":117,"91":89,"92":132,"93":141,"94":86,"95":153,"96":116,"97":98,"98":140,"99":93,"100":115,"101":161,"102":119,"103":129,"104":105,"105":107,"106":95,"107":132,"108":238,"109":129,"110":130,"111":124,"112":109,"113":100,"114":122,"115":111,"116":88,"117":172,"118":127,"119":126,"120":91,"121":148,"122":110,"123":138,"124":135,"125":107,"126":103,"127":158,"128":130,"129":118,"130":178,"131":162,"132":179,"133":3,"134":130,"135":138,"136":97,"137":121,"138":68,"139":140,"140":161,"141":132,"142":156,"143":119,"144":165,"145":127,"146":89,"147":102,"148":132,"149":138,"150":153,"151":123,"152":114,"153":170,"154":96,"155":131,"156":129,"157":129,"158":170,"159":160,"160":116,"161":107,"162":143,"163":125,"164":136,"165":122,"166":128,"167":136,"168":218,"169":99,"170":119,"171":142,"172":115,"173":99,"174":108,"175":149,"176":126,"177":131,"178":143,"179":103,"180":103,"181":170,"182":102,"183":130,"184":106,"185":126,"186":229,"187":134,"188":181,"189":178,"190":81,"191":105,"192":122,"193":153,"194":160,"195":2,"196":164,"197":95,"198":122,"199":117,"200":137,"201":116,"202":149,"203":125,"204":146,"205":88,"206":110,"207":137,"208":98,"209":165,"210":115,"211":113,"212":147,"213":87,"214":117,"215":155,"216":112,"217":165,"218":87,"219":112,"220":89,"221":133,"222":102,"223":106,"224":130,"225":106,"226":119,"227":151,"228":155,"229":88,"230":110,"231":132,"232":150,"233":109,"234":125,"235":116,"236":137,"237":121,"238":189,"239":169,"240":116,"241":169,"242":130,"243":118,"244":130,"245":207,"246":127,"247":133,"248":145},"Descriptions":{"0":"Two imprisoned men bond over a number of years, finding solace and eventual redemption through acts of common decency.","1":"The aging patriarch of an organized crime dynasty in postwar New York City transfers control of his clandestine empire to his reluctant youngest son.","2":"When the menace known as the Joker wreaks havoc and chaos on the people of Gotham, Batman must accept one of the greatest psychological and physical tests of his ability to fight injustice.","3":"The early life and career of Vito Corleone in 1920s New York City is portrayed, while his son, Michael, expands and tightens his grip on the family crime syndicate.","4":"The jury in a New York City murder trial is frustrated by a single member whose skeptical caution forces them to more carefully consider the evidence before jumping to a hasty verdict.","5":"In German-occupied Poland during World War II, industrialist Oskar Schindler gradually becomes concerned for his Jewish workforce after witnessing their persecution by the Nazis.","6":"Gandalf and Aragorn lead the World of Men against Sauron's army to draw his gaze from Frodo and Sam as they approach Mount Doom with the One Ring.","7":"The lives of two mob hitmen, a boxer, a gangster and his wife, and a pair of diner bandits intertwine in four tales of violence and redemption.","8":"A meek Hobbit from the Shire and eight companions set out on a journey to destroy the powerful One Ring and save Middle-earth from the Dark Lord Sauron.","9":"A bounty hunting scam joins two men in an uneasy alliance against a third in a race to find a fortune in gold buried in a remote cemetery.","10":"The presidencies of Kennedy and Johnson, the Vietnam War, the Watergate scandal and other historical events unfold from the perspective of an Alabama man with an IQ of 75, whose only desire ...","11":"An insomniac office worker and a devil-may-care soap maker form an underground fight club that evolves into much more.","12":"While Frodo and Sam edge closer to Mordor with the help of the shifty Gollum, the divided fellowship makes a stand against Sauron's new ally, Saruman, and his hordes of Isengard.","13":"A thief who steals corporate secrets through the use of dream-sharing technology is given the inverse task of planting an idea into the mind of a C.E.O., but his tragic past may doom the pro...","14":"After the Rebels are brutally overpowered by the Empire on the ice planet Hoth, Luke Skywalker begins Jedi training with Yoda, while his friends are pursued across the galaxy by Darth Vader ...","15":"When a beautiful stranger leads computer hacker Neo to a forbidding underworld, he discovers the shocking truth--the life he knows is the elaborate deception of an evil cyber-intelligence.","16":"The life of the lawyer who became the famed leader of the Indian revolts against the British rule through his philosophy of nonviolent protest.","17":"An aspiring author during the civil rights movement of the 1960s decides to write a book detailing the African American maids' point of view on the white families for which they work, and th...","18":"A young boy befriends a giant robot from outer space that a paranoid government agent wants to destroy.","19":"A kindhearted street urchin and a power-hungry Grand Vizier vie for a magic lamp that has the power to make their deepest wishes come true.","20":"The Russian army sends an explorer on an expedition to the snowy Siberian wilderness where he makes friends with a seasoned local hunter.","21":"An aging Chinese immigrant is swept up in an insane adventure, in which she alone can save the world by exploring other universes connecting with the lives she could have led.","22":"Born on the original Christmas in the stable next door to Jesus Christ, Brian of Nazareth spends his life being mistaken for a messiah.","23":"A young novitiate is sent by her convent in 1930s Austria to become a governess to the seven children of a widowed naval officer.","24":"A nurse is put in charge of a mute actress and finds that their personae are melding together.","25":"A renegade reporter trailing a young runaway heiress for a big story joins her on a bus heading from Florida to New York, and they end up stuck with each other when the bus leaves them behin...","26":"A woman is hired as a handmaiden to a Japanese heiress, but secretly she is involved in a plot to defraud her.","27":"A young boy, left without attention, delves into a life of petty crime.","28":"A laid back Southern man is sentenced to two years in a rural prison, but refuses to conform.","29":"A horrific car accident connects three stories, each involving characters dealing with loss, regret, and life's harsh realities, all in the name of love.","30":"A self-conscious woman juggles adjusting to her new role as an aristocrat's wife and avoiding being intimidated by his first wife's spectral presence.","31":null,"32":"An Oklahoma family, driven off their farm by the poverty and hopelessness of the Dust Bowl, joins the westward migration to California, suffering the misfortunes of the homeless in the Great...","33":"Blacksmith Will Turner teams up with eccentric pirate \"Captain\" Jack Sparrow to save his love, the governor's daughter, from Jack's former pirate allies, who are now undead.","34":"When a tribal man is arrested for a case of alleged theft, his wife turns to a human-rights lawyer to help bring justice.","35":"24 hours in the lives of three young men in the French suburbs the day after a violent riot.","36":"A college professor bonds with an abandoned dog he takes into his home.","37":"In the 1950s, fear and violence escalate as the people of Algiers fight for independence from the French government.","38":null,"39":"While trying to lead a quiet suburban life, a family of undercover superheroes are forced into action to save the world.","40":"Three World War II veterans, two of them traumatized or disabled, return home to the American midwest to discover that they and their families have been irreparably changed.","41":"When a teenage girl is possessed by a mysterious entity, her mother seeks the help of two priests to save her daughter.","42":"A narcissistic, self-centered weatherman finds himself in a time loop on Groundhog Day, and the day keeps repeating until he gets it right.","43":"Nine years after Jesse and Celine first met, they encounter each other again on the French leg of Jesse's book tour.","44":"Young Dorothy Gale and her dog Toto are swept away by a tornado from their Kansas farm to the magical Land of Oz, and embark on a quest with three new friends to see the Wizard, who can retu...","45":"After graduating from Emory University, top student and athlete Christopher McCandless abandons his possessions, gives his entire $24,000 savings account to charity and hitchhikes to Alaska ...","46":"A television network cynically exploits a deranged former anchor's ravings and revelations about the news media for its own profit, but finds that his message may be difficult to control.","47":"Impoverished priest Harihar Ray, dreaming of a better life for himself and his family, leaves his rural Bengal village in search of work.","48":"The merciless 1970s rivalry between Formula One rivals James Hunt and Niki Lauda.","49":"A rat who can cook makes an unusual alliance with a young kitchen worker at a famous Paris restaurant.","50":"In a future where mutants are nearly extinct, an elderly and weary Logan leads a quiet life. But when Laura, a mutant child pursued by scientists, comes to him for help, he must get her to s...","51":"After the death of one of his friends, a writer recounts a childhood journey with his friends to find the body of a missing boy.","52":"A human soldier is sent from 2029 to 1984 to stop an almost indestructible cyborg killing machine, sent from the same year, which has been programmed to execute a young woman whose unborn so...","53":"The true story of how the Boston Globe uncovered the massive scandal of child molestation and cover-up within the local Catholic Archdiocese, shaking the entire Catholic Church to its core.","54":"Chris Taylor, a neophyte recruit in Vietnam, finds himself caught in a battle of wills between two sergeants, one good and the other evil. A shrewd examination of the brutality of war and th...","55":"A small-time Philadelphia boxer gets a supremely rare chance to fight the world heavyweight champion in a bout in which he strives to go the distance for his self-respect.","56":"American car designer Carroll Shelby and driver Ken Miles battle corporate interference and the laws of physics to build a revolutionary race car for Ford in order to defeat Ferrari at the 2...","57":"Paul Rusesabagina, a hotel manager, houses over a thousand Tutsi refugees during their struggle against the Hutu militia in Rwanda, Africa.","58":"An old couple visit their children and grandchildren in the city, but receive little attention.","59":"In 1431, Jeanne d'Arc is placed on trial on charges of heresy. The ecclesiastical jurists attempt to force Jeanne to recant her claims of holy visions.","60":"Maverick teacher John Keating uses poetry to embolden his boarding school students to new heights of self-expression.","61":"When a killer shark unleashes chaos on a beach community off Cape Cod, it's up to a local sheriff, a marine biologist, and an old seafarer to hunt the beast down.","62":"Ultimate L.A. slacker Jeff \"The Dude\" Lebowski, mistaken for a millionaire of the same name, seeks restitution for a rug ruined by debt collectors, enlisting his bowling buddies for help whi...","63":"In order to power the city, monsters have to scare children so that they scream. However, the children are toxic to the monsters, and after a child gets through, two monsters realize things ...","64":"A hapless young Viking who aspires to hunt dragons becomes the unlikely friend of a young dragon himself, and learns there may be more to the creatures than he assumed.","65":"A tale of friendship between two unlikely pen pals: Mary, a lonely, eight-year-old girl living in the suburbs of Melbourne, and Max, a forty-four-year old, severely obese man living in New Y...","66":"Held captive for 7 years in an enclosed space, a woman and her young son finally gain their freedom, allowing the boy to experience the outside world for the first time.","67":"In a post-apocalyptic wasteland, a woman rebels against a tyrannical ruler in search for her homeland with the aid of a group of female prisoners, a psychotic worshiper, and a drifter named ...","68":null,"69":"Six short stories that explore the extremities of human behavior involving people in distress.","70":"In a small Korean province in 1986, two detectives struggle with the case of multiple young women being found raped and murdered by an unknown culprit.","71":"A naive youth leader is appointed to fill a vacancy in the U.S. Senate. His idealistic plans promptly collide with corruption at home and subterfuge from his hero in Washington, but he tries...","72":"A film projectionist longs to be a detective, and puts his meagre skills to work when he is framed by a rival for stealing his girlfriend's father's pocketwatch.","73":"World War II American Army Medic Desmond T. Doss, who served during the Battle of Okinawa, refuses to kill people and becomes the first man in American history to receive the Medal of Honor ...","74":"In a decrepit South American village, four men are hired to transport an urgent nitroglycerine shipment without the equipment that would make it safe.","75":"An Irish rogue wins the heart of a rich widow and assumes her dead husband's aristocratic position in 18th-century England.","76":"A simple act of kindness always sparks another, even in a frozen, faraway place. When Smeerensburg's new postman, Jesper, befriends toymaker Klaus, their gifts melt an age-old feud and deliv...","77":null,"78":"An in-depth examination of the ways in which the Vietnam War impacts and disrupts the lives of several friends in a small steel mill town in Pennsylvania.","79":"A writer encounters the owner of an aging high-class hotel, who tells him of his early years serving as a lobby boy in the hotel's glorious years under an exceptional concierge.","80":"Pulp novelist Holly Martins travels to shadowy, postwar Vienna, only to find himself investigating the mysterious death of an old friend, Harry Lime.","81":"After being rejected by the Confederate military, not realizing it was due to his crucial civilian role, an engineer must single-handedly recapture his beloved locomotive after it is seized ...","82":"With his wife's disappearance having become the focus of an intense media circus, a man sees the spotlight turned on him when it's suspected that he may not be innocent.","83":null,"84":"After a Jewish prince is betrayed and sent into slavery by a Roman friend in 1st-century Jerusalem, he regains his freedom and comes back for revenge.","85":"Harry, Ron, and Hermione search for Voldemort's remaining Horcruxes in their effort to destroy the Dark Lord as the final battle rages on at Hogwarts.","86":"In the antebellum United States, Solomon Northup, a free black man from upstate New York, is abducted and sold into slavery.","87":"A young man and woman meet on a train in Europe, and wind up spending one evening together in Vienna. Unfortunately, both know that this will probably be their only night together.","88":"An ex-prize fighter turned New Jersey longshoreman struggles to stand up to his corrupt union bosses, including his older brother, as he starts to connect with the grieving sister of one of ...","89":"A prospector goes to the Klondike during the 1890s gold rush in hopes of making his fortune, and is smitten with a girl he sees in a dance hall.","90":"A blade runner must pursue and terminate four replicants who stole a ship in space and have returned to Earth to find their creator.","91":"After a boy loses his sister's pair of shoes, he goes on a series of adventures in order to find them. When he can't, he tries a new way to \"win\" a new pair.","92":"A determined woman works with a hardened boxing trainer to become a professional.","93":"Barely 21 yet, Frank is a skilled forger who has passed as a doctor, lawyer and pilot. FBI agent Carl becomes obsessed with tracking down the con man, who only revels in the pursuit.","94":"When two girls move to the country to be near their ailing mother, they have adventures with the wondrous forest spirits who live nearby.","95":"When Keller Dover's daughter and her friend go missing, he takes matters into his own hands as the police pursue multiple leads and the pressure mounts.","96":"Disgruntled Korean War veteran Walt Kowalski sets out to reform his neighbor, Thao Lor, a Hmong teenager who tried to steal Kowalski's prized possession: a 1972 Gran Torino.","97":"Minnesota car salesman Jerry Lundegaard's inept crime falls apart due to his and his henchmen's bungling and the persistent police work of the quite pregnant Marge Gunderson.","98":"The youngest son of an alcoholic former boxer returns home, where he's trained by his father for competition in a mixed martial arts tournament - a path that puts the fighter on a collision ...","99":"Renton, deeply immersed in the Edinburgh drug scene, tries to clean up and get out, despite the allure of the drugs and influence of friends.","100":"A mother personally challenges the local authorities to solve her daughter's murder when they fail to catch the culprit.","101":"British POWs are forced to build a railway bridge across the river Kwai for their Japanese captors in occupied Burma, not knowing that the allied forces are planning a daring commando raid t...","102":"When an unconfident young woman is cursed with an old body by a spiteful witch, her only chance of breaking the spell lies with a self-indulgent yet insecure young wizard and his companions ...","103":"A retired legal counselor writes a novel hoping to find closure for one of his past unresolved homicide cases and for his unreciprocated love with his superior - both of which still haunt hi...","104":"A former tennis star arranges the murder of his adulterous wife.","105":"Eddy persuades his three pals to pool money for a vital poker game against a powerful local mobster, Hatchet Harry. Eddy loses, after which Harry gives him a week to pay back 500,000 pounds.","106":"After young Riley is uprooted from her Midwest life and moved to San Francisco, her emotions - Joy, Fear, Anger, Disgust and Sadness - conflict on how best to navigate a new city, house, and...","107":"In a future British dystopian society, a shadowy freedom fighter, known only by the alias of \"V\", plots to overthrow the tyrannical government - with the help of a young woman.","108":"The manipulative daughter of a Georgia plantation owner conducts a turbulent romance with a roguish profiteer during the American Civil War and Reconstruction periods.","109":"The life of boxer Jake LaMotta, whose violence and temper that led him to the top in the ring destroyed his life outside of it.","110":"A private detective hired to expose an adulterer in 1930s Los Angeles finds himself caught up in a web of deceit, corruption, and murder.","111":"A Victorian surgeon rescues a heavily disfigured man who is mistreated while scraping a living as a side-show freak. Behind his monstrous fa\u00c3\u00a7ade, there is revealed a person of kindness, inte...","112":"A research team in Antarctica is hunted by a shape-shifting alien that assumes the appearance of its victims.","113":"After his son is captured in the Great Barrier Reef and taken to Sydney, a timid clownfish sets out on a journey to bring him home.","114":"Violence and mayhem ensue after a hunter stumbles upon a drug deal gone wrong and more than two million dollars in cash near the Rio Grande.","115":"After awakening from a four-year coma, a former assassin wreaks vengeance on the team of assassins who betrayed her.","116":"The rape of a bride and the murder of her samurai husband are recalled from the perspectives of a bandit, the bride, the samurai's ghost and a woodcutter.","117":"Allied prisoners of war plan for several hundred of their number to escape from a German camp during World War II.","118":"A pragmatic paleontologist touring an almost complete theme park on an island in Central America is tasked with protecting a couple of kids after a power failure causes the park's cloned din...","119":"Two down-on-their-luck Americans searching for work in 1920s Mexico convince an old prospector to help them mine for gold in the Sierra Madre Mountains.","120":"King Arthur and his Knights of the Round Table embark on a surreal, low-budget search for the Holy Grail, encountering many, very silly obstacles.","121":"With Spider-Man's identity now revealed, Peter asks Doctor Strange for help. When a spell goes wrong, dangerous foes from other worlds start to appear, forcing Peter to discover what it trul...","122":"A crafty ronin comes to a town divided by two criminal gangs and decides to play them against each other to free the town.","123":"In 1954, a U.S. Marshal investigates the disappearance of a murderer who escaped from a hospital for the criminally insane.","124":"After John Nash, a brilliant but asocial mathematician, accepts secret work in cryptography, his life takes a turn for the nightmarish.","125":"A frightened, withdrawn Philadelphia boy who communicates with spirits seeks the help of a disheartened child psychologist.","126":"An insurance salesman discovers his whole life is actually a reality TV show.","127":"A story of family, religion, hatred, oil and madness, focusing on a turn-of-the-century prospector in the early days of the business.","128":"Retired Old West gunslinger William Munny reluctantly takes on one last job, with the help of his old partner Ned Logan and a young man, The \"Schofield Kid.\"","129":"In the Falangist Spain of 1944, the bookish young stepdaughter of a sadistic army officer escapes into an eerie but captivating fantasy world.","130":"A tale of greed, deception, money, power, and murder occur between two best friends: a mafia enforcer and a casino executive compete against each other over a gambling empire, and over a fas...","131":"In Medieval Japan, an elderly warlord retires, handing over his empire to his three sons. However, he vastly underestimates how the new-found power will corrupt them and cause them to turn o...","132":"In 1948, an American court in occupied Germany tries four Nazis judged for war crimes.","133":"Based on the true story of Jordan Belfort, from his rise to a wealthy stock-broker living the high life to his fall involving crime, corruption and the federal government.","134":"A working-class Italian-American bouncer becomes the driver for an African-American classical pianist on a tour of venues through the 1960s American South.","135":"A seemingly timid but secretly ruthless ing\u00c3\u00a9nue insinuates herself into the lives of an aging Broadway star and her circle of theater friends.","136":"A man refuses all assistance from his daughter as he ages. As he tries to make sense of his changing circumstances, he begins to doubt his loved ones, his own mind and even the fabric of his...","137":"After two male musicians witness a mob hit, they flee the state in an all-female band disguised as women, but further complications set in.","138":null,"139":"After training with his mentor, Batman begins his fight to free crime-ridden Gotham City from corruption.","140":"Former wrestler Mahavir Singh Phogat and his two wrestler daughters struggle towards glory at the Commonwealth Games in the face of societal oppression.","141":"Two bounty hunters with the same intentions team up to track down an escaped Mexican outlaw.","142":null,"143":"April 6th, 1917. As an infantry battalion assembles to wage war deep in enemy territory, two soldiers are assigned to race against time and deliver a message that will stop 1,600 men from wa...","144":"An eight-year-old boy is thought to be a lazy trouble-maker, until the new art teacher has the patience and compassion to discover the real problem behind his struggles in school.","145":"In 1938, after his father Professor Henry Jones, Sr. goes missing while pursuing the Holy Grail, Professor Henry \"Indiana\" Jones, Jr. finds himself up against Adolf Hitler's Nazis again to s...","146":"In post-war Italy, a working-class man's bicycle is stolen, endangering his efforts to find work. He and his son set out to find it.","147":"Unscrupulous boxing promoters, violent bookmakers, a Russian gangster, incompetent amateur robbers and supposedly Jewish jewelers fight to track down a priceless stolen diamond.","148":"A New York City police officer tries to save his estranged wife and several others taken hostage by terrorists during a Christmas party at the Nakatomi Plaza in Los Angeles.","149":"As corruption grows in 1950s Los Angeles, three policemen - one strait-laced, one brutal, and one sleazy - investigate a series of murders with their own brand of justice.","150":"In a futuristic city sharply divided between the working class and the city planners, the son of the city's mastermind falls in love with a working-class prophet who predicts the coming of a...","151":"A married couple are faced with a difficult decision - to improve the life of their child by moving to another country or to stay in Iran and look after a deteriorating parent who has Alzhei...","152":"A mentally unstable veteran works as a nighttime taxi driver in New York City, where the perceived decadence and sleaze fuels his urge for violent action.","153":"A group of high-end professional thieves start to feel the heat from the LAPD when they unknowingly leave a clue at their latest heist.","154":"78-year-old Carl Fredricksen travels to Paradise Falls in his house equipped with balloons, inadvertently taking a young stowaway.","155":"Twins journey to the Middle East to discover their family history and fulfill their mother's last wishes.","156":"Two grifters team up to pull off the ultimate con.","157":"Atticus Finch, a widowed lawyer in Depression-era Alabama, defends a black man against an undeserved rape charge, and his children against prejudice.","158":"In 1980 Miami, a determined Cuban immigrant takes over a drug cartel and succumbs to greed.","159":"The real life of one of America's foremost founding fathers and first Secretary of the Treasury, Alexander Hamilton. Captured live on Broadway from the Richard Rodgers Theater with the origi...","160":"A pragmatic U.S. Marine observes the dehumanizing effects the Vietnam War has on his fellow recruits from their brutal boot camp training to the bloody street fighting in Hue.","161":"A Los Angeles insurance representative lets an alluring housewife seduce him into a scheme of insurance fraud and murder that arouses the suspicion of his colleague, an insurance investigato...","162":"A bureaucrat tries to find meaning in his life after he discovers he has terminal cancer.","163":"A Manhattan insurance clerk tries to rise in his company by letting its executives use his apartment for trysts, but complications and a romance of his own ensue.","164":"In the future, a sadistic gang leader is imprisoned and volunteers for a conduct-aversion experiment, but it doesn't go as planned.","165":"Am\u00c3\u00a9lie is an innocent and naive girl in Paris with her own sense of justice. She decides to help those around her and, along the way, discovers love.","166":"A former San Francisco police detective juggles wrestling with his personal demons and becoming obsessed with the hauntingly beautiful woman he has been hired to trail, who may be deeply dis...","167":"A New York City advertising executive goes on the run after being mistaken for a government agent by a group of foreign spies, and falls for a woman whose loyalties he begins to doubt.","168":"The story of T.E. Lawrence, the English officer who successfully united and led the diverse, often warring, Arab tribes during World War I in order to fight the Turks.","169":"When the police in a German city are unable to catch a child-murderer, other criminals join in the manhunt.","170":"Following the death of publishing tycoon Charles Foster Kane, reporters scramble to uncover the meaning of his final utterance: 'Rosebud.'","171":"After finding an old rifle, a young boy joins the Soviet resistance movement against ruthless German forces and experiences the horrors of World War II.","172":"A teacher lives a lonely life, all the while struggling over his son's custody. His life slowly gets better as he finds love and receives good news from his son, but his new luck is about to...","173":"When a simple jewelry heist goes horribly wrong, the surviving criminals begin to suspect that one of them is a police informant.","174":"When their relationship turns sour, a couple undergoes a medical procedure to have each other erased from their memories for ever.","175":"After uncovering a mysterious artifact buried beneath the Lunar surface, a spacecraft is sent to Jupiter to find its origins - a spacecraft manned by two men and the supercomputer H.A.L. 900...","176":"While serving a five-year sentence for a violent crime, a 12-year-old boy sues his parents for neglect.","177":"After a daring mission to rescue Han Solo from Jabba the Hutt, the Rebels dispatch to Endor to destroy the second Death Star. Meanwhile, Luke struggles to help Darth Vader back from the dark...","178":"An executive of a Yokohama shoe company becomes a victim of extortion when his chauffeur's son is kidnapped by mistake and held for ransom.","179":"The toys are mistakenly delivered to a day-care center instead of the attic right before Andy leaves for college, and it's up to Woody to convince the other toys that they weren't abandoned ...","180":"A silent film star falls for a chorus girl just as he and his delusionally jealous screen partner are trying to make the difficult transition to talking pictures in 1920s Hollywood.","181":"Two friends are searching for their long lost companion. They revisit their college days and recall the memories of their friend who inspired them to think differently, even as the rest of t...","182":"The drug-induced utopias of four Coney Island people are shattered when their addictions run deep.","183":"After thirty years, Maverick is still pushing the envelope as a top naval aviator, but must confront ghosts of his past when he leads TOP GUN's elite graduates on a mission that demands the ...","184":"Two strangers find themselves linked in a bizarre way. When a connection forms, will distance be the only thing to keep them apart?","185":"Will Hunting, a janitor at M.I.T., has a gift for mathematics, but needs help from a psychologist to find direction in his life.","186":"A former Prohibition-era Jewish gangster returns to the Lower East Side of Manhattan 35 years later, where he must once again confront the ghosts and regrets of his old life.","187":"On a journey to find the cure for a Tatarigami's curse, Ashitaka finds himself in the middle of a war between the forest gods and Tatara, a mining colony. In this quest he also meets San, th...","188":"After the devastating events of Avengers: Infinity War (2018), the universe is in ruins. With the help of remaining allies, the Avengers assemble once more in order to reverse Thanos' action...","189":"Scottish warrior William Wallace leads his countrymen in a rebellion to free his homeland from the tyranny of King Edward I of England.","190":"A cowboy doll is profoundly threatened and jealous when a new spaceman action figure supplants him as top toy in a boy's bedroom.","191":"Aspiring musician Miguel, confronted with his family's ancestral ban on music, enters the Land of the Dead to find his great-great-grandfather, a legendary singer.","192":"A mentally troubled stand-up comedian embarks on a downward spiral that leads to the creation of an iconic villain.","193":"In Nazi-occupied France during World War II, a plan to assassinate Nazi leaders by a group of Jewish U.S. soldiers coincides with a theatre owner's vengeful plans for the same.","194":"The life, success and troubles of Wolfgang Amadeus Mozart, as told by Antonio Salieri, the contemporaneous composer who was deeply jealous of Mozart's talent and claimed to have murdered him...","195":"After being kidnapped and imprisoned for fifteen years, Oh Dae-Su is released, only to find that he must find his captor in five days.","196":"Eight years after the Joker's reign of anarchy, Batman, with the help of the enigmatic Selina Kyle, is forced from his exile to save Gotham City from the brutal guerrilla terrorist Bane.","197":"An insane American general orders a bombing attack on the Soviet Union, triggering a path to nuclear holocaust that a war room full of politicians and generals frantically tries to stop.","198":"A sexually frustrated suburban father has a mid-life crisis after becoming infatuated with his daughter's best friend.","199":"Teen Miles Morales becomes the Spider-Man of his universe, and must join with five spider-powered individuals from other dimensions to stop a threat for all realities.","200":"Fifty-seven years after surviving an apocalyptic attack aboard her space vessel by merciless space creatures, Officer Ripley awakens from hyper-sleep and tries to warn anyone who will listen...","201":"A veteran British barrister must defend his client in a murder trial that has surprise after surprise.","202":"The Avengers and their allies must be willing to sacrifice all in an attempt to defeat the powerful Thanos before his blitz of devastation and ruin puts an end to the universe.","203":"Dictator Adenoid Hynkel tries to expand his empire while a poor Jewish barber tries to avoid persecution from Hynkel's regime.","204":"A family heads to an isolated hotel for the winter where a sinister presence influences the father into violence, while his psychic son sees horrific forebodings from both past and future.","205":"After refusing to attack an enemy position, a general accuses the soldiers of cowardice and their commanding officer must defend them.","206":"A screenwriter develops a dangerous relationship with a faded film star determined to make a triumphant return.","207":null,"208":"In the distant future, a small waste-collecting robot inadvertently embarks on a space journey that will ultimately decide the fate of mankind.","209":"With the help of a German bounty-hunter, a freed slave sets out to rescue his wife from a brutal plantation-owner in Mississippi.","210":"Archaeology professor Indiana Jones ventures to seize a biblical artefact known as the Ark of the Covenant. While doing so, he puts up a fight against Renee and a troop of Nazis.","211":"A man with short-term memory loss attempts to track down his wife's murderer.","212":"A U.S. Army officer serving in Vietnam is tasked with assassinating a renegade Special Forces Colonel who sees himself as a god.","213":null,"214":"The crew of a commercial spacecraft encounter a deadly lifeform after investigating an unknown transmission.","215":"A filmmaker recalls his childhood when falling in love with the pictures at the cinema of his home village and forms a deep friendship with the cinema's projectionist.","216":"A wheelchair-bound photographer spies on his neighbors from his Greenwich Village courtyard apartment window, and becomes convinced one of them has committed murder, despite the skepticism o...","217":"A mysterious stranger with a harmonica joins forces with a notorious desperado to protect a beautiful widow from a ruthless assassin working for the railroad.","218":"The Tramp struggles to live in modern industrial society with the help of a young homeless woman.","219":"After he becomes a quadriplegic from a paragliding accident, an aristocrat hires a young man from the projects to be his caregiver.","220":"A young boy and his little sister struggle to survive in Japan during World War II.","221":null,"222":"A cynical expatriate American cafe owner struggles to decide whether or not to help his former lover and her fugitive husband escape the Nazis in French Morocco.","223":"A promising young drummer enrolls at a cut-throat music conservatory where his dreams of greatness are mentored by an instructor who will stop at nothing to realize a student's potential.","224":"After a tragic accident, two stage magicians in 1890s London engage in a battle to create the ultimate illusion while sacrificing everything they have to outwit each other.","225":"A sole survivor tells of the twisty events leading up to a horrific gun battle on a boat, which began when five criminals met at a seemingly random police lineup.","226":"A former neo-nazi skinhead tries to prevent his younger brother from going down the same wrong path that he did.","227":"An undercover cop and a mole in the police attempt to identify each other while infiltrating an Irish gang in South Boston.","228":"A former Roman General sets out to exact vengeance against the corrupt emperor who murdered his family and sent him into slavery.","229":"Lion prince Simba and his father are targeted by his bitter uncle, who wants to ascend the throne himself.","230":"12-year-old Mathilda is reluctantly taken in by L\u00c3\u00a9on, a professional assassin, after her family is murdered. An unusual relationship forms as she becomes his prot\u00c3\u00a9g\u00c3\u00a9e and learns the assassin...","231":"Greed and class discrimination threaten the newly formed symbiotic relationship between the wealthy Park family and the destitute Kim clan.","232":"A Polish Jewish musician struggles to survive the destruction of the Warsaw ghetto of World War II.","233":"A Phoenix secretary embezzles $40,000 from her employer's client, goes on the run and checks into a remote motel run by a young man under the domination of his mother.","234":"During her family's move to the suburbs, a sullen 10-year-old girl wanders into a world ruled by gods, witches, and spirits, and where humans are changed into beasts.","235":"Marty McFly, a 17-year-old high school student, is accidentally sent 30 years into the past in a time-traveling DeLorean invented by his close friend, the maverick scientist Doc Brown.","236":"A cyborg, identical to the one who failed to kill Sarah Connor, must now protect her 10-year old adolescent son John from an even more advanced and powerful cyborg.","237":"Luke Skywalker joins forces with a Jedi Knight, a cocky pilot, a Wookiee and two droids to save the galaxy from the Empire's world-destroying battle station, while also attempting to rescue ...","238":"The lives of guards on Death Row are affected by one of their charges: a black man accused of child murder and rape, yet who has a mysterious gift.","239":"A team of explorers travel through a wormhole in space in an attempt to ensure humanity's survival.","240":"When an open-minded Jewish waiter and his son become victims of the Holocaust, he uses a perfect mixture of will, humor, and imagination to protect his son from the dangers around their camp...","241":"Following the Normandy Landings, a group of U.S. soldiers go behind enemy lines to retrieve a paratrooper whose brothers have been killed in action.","242":"In the slums of Rio, two kids' paths diverge as one struggles to become a photographer and the other a kingpin.","243":"A young F.B.I. cadet must receive the help of an incarcerated and manipulative cannibal killer to help catch another serial killer, a madman who skins his victims.","244":"An angel is sent from Heaven to help a desperately frustrated businessman by showing him what life would have been like if he had never existed.","245":"Farmers from a village exploited by bandits hire a veteran samurai for protection, who gathers six other samurai to join him.","246":"Two detectives, a rookie and a veteran, hunt a serial killer who uses the seven deadly sins as his motives.","247":"In the Fall of 1963, a Korean War veteran and criminal pleads insanity and is admitted to a mental institution, where he rallies up the scared patients against the tyrannical nurse.","248":"The story of Henry Hill and his life in the mob, covering his relationship with his wife Karen Hill and his mob partners Jimmy Conway and Tommy DeVito in the Italian-American crime syndicate..."},"Acteurs":{"0":"Tim Robbins,Morgan Freeman,Bob Gunton","1":"Marlon Brando,Al Pacino,James Caan","2":"Christian Bale,Heath Ledger,Aaron Eckhart","3":"Al Pacino,Robert De Niro,Robert Duvall","4":"Henry Fonda,Lee J. Cobb,Martin Balsam","5":"Liam Neeson,Ralph Fiennes,Ben Kingsley","6":"Elijah Wood,Viggo Mortensen,Ian McKellen","7":"John Travolta,Uma Thurman,Samuel L. Jackson","8":"Elijah Wood,Ian McKellen,Orlando Bloom","9":"Clint Eastwood,Eli Wallach,Lee Van Cleef","10":"Tom Hanks,Robin Wright,Gary Sinise","11":"Brad Pitt,Edward Norton,Meat Loaf","12":"Elijah Wood,Ian McKellen,Viggo Mortensen","13":"Leonardo DiCaprio,Joseph Gordon-Levitt,Elliot Page","14":"Mark Hamill,Harrison Ford,Carrie Fisher","15":"Keanu Reeves,Laurence Fishburne,Carrie-Anne Moss","16":"Ben Kingsley,John Gielgud,Rohini Hattangadi","17":"Viola Davis,Emma Stone,Octavia Spencer","18":"Eli Marienthal,Harry Connick Jr.,Jennifer Aniston","19":"Scott Weinger,Robin Williams,Linda Larkin","20":"Maksim Munzuk,Yuriy Solomin,Mikhail Bychkov","21":"Michelle Yeoh,Stephanie Hsu,Jamie Lee Curtis","22":"Graham Chapman,John Cleese,Michael Palin","23":"Julie Andrews,Christopher Plummer,Eleanor Parker","24":"Bibi Andersson,Liv Ullmann,Margaretha Krook","25":"Clark Gable,Claudette Colbert,Walter Connolly","26":"Kim Min-hee,Ha Jung-woo,Cho Jin-woong","27":"Jean-Pierre L\u00c3\u00a9aud,Albert R\u00c3\u00a9my,Claire Maurier","28":"Paul Newman,George Kennedy,Strother Martin","29":"Emilio Echevarr\u00c3\u00ada,Gael Garc\u00c3\u00ada Bernal,Goya Toledo","30":"Laurence Olivier,Joan Fontaine,George Sanders","31":"\u00c3\u0087etin Tekindor,Fikret Kuskan,H\u00c3\u00bcmeyra","32":"Henry Fonda,Jane Darwell,John Carradine","33":"Johnny Depp,Geoffrey Rush,Orlando Bloom","34":"Suriya,Lijo Mol Jose,Manikandan K.","35":"Vincent Cassel,Hubert Kound\u00c3\u00a9,Sa\u00c3\u00afd Taghmaoui","36":"Richard Gere,Joan Allen,Cary-Hiroyuki Tagawa","37":"Brahim Hadjadj,Jean Martin,Yacef Saadi","38":"Carole Lombard,Jack Benny,Robert Stack","39":"Craig T. Nelson,Samuel L. Jackson,Holly Hunter","40":"Myrna Loy,Dana Andrews,Fredric March","41":"Ellen Burstyn,Max von Sydow,Linda Blair","42":"Bill Murray,Andie MacDowell,Chris Elliott","43":"Ethan Hawke,Julie Delpy,Vernon Dobtcheff","44":"Judy Garland,Frank Morgan,Ray Bolger","45":"Emile Hirsch,Vince Vaughn,Catherine Keener","46":"Faye Dunaway,William Holden,Peter Finch","47":"Kanu Bannerjee,Karuna Bannerjee,Subir Banerjee","48":"Daniel Br\u00c3\u00bchl,Chris Hemsworth,Olivia Wilde","49":"Brad Garrett,Lou Romano,Patton Oswalt","50":"Hugh Jackman,Patrick Stewart,Dafne Keen","51":"Wil Wheaton,River Phoenix,Corey Feldman","52":"Arnold Schwarzenegger,Linda Hamilton,Michael Biehn","53":"Mark Ruffalo,Michael Keaton,Rachel McAdams","54":"Charlie Sheen,Tom Berenger,Willem Dafoe","55":"Sylvester Stallone,Talia Shire,Burt Young","56":"Matt Damon,Christian Bale,Jon Bernthal","57":"Don Cheadle,Sophie Okonedo,Joaquin Phoenix","58":"Chish\u00c3\u00bb Ry\u00c3\u00bb,Chieko Higashiyama,S\u00c3\u00b4 Yamamura","59":"Maria Falconetti,Eugene Silvain,Andr\u00c3\u00a9 Berley","60":"Robin Williams,Robert Sean Leonard,Ethan Hawke","61":"Roy Scheider,Robert Shaw,Richard Dreyfuss","62":"Jeff Bridges,John Goodman,Julianne Moore","63":"Billy Crystal,John Goodman,Mary Gibbs","64":"Jay Baruchel,Gerard Butler,Christopher Mintz-Plasse","65":"Toni Collette,Philip Seymour Hoffman,Eric Bana","66":"Brie Larson,Jacob Tremblay,Sean Bridgers","67":"Tom Hardy,Charlize Theron,Nicholas Hoult","68":"Max von Sydow,Gunnar Bj\u00c3\u00b6rnstrand,Bengt Ekerot","69":"Dar\u00c3\u00ado Grandinetti,Mar\u00c3\u00ada Marull,M\u00c3\u00b3nica Villa","70":"Song Kang-ho,Kim Sang-kyung,Roe-ha Kim","71":"James Stewart,Jean Arthur,Claude Rains","72":"Buster Keaton,Kathryn McGuire,Joe Keaton","73":"Andrew Garfield,Sam Worthington,Luke Bracey","74":"Yves Montand,Charles Vanel,Peter van Eyck","75":"Ryan O'Neal,Marisa Berenson,Patrick Magee","76":"Jason Schwartzman,J.K. Simmons,Rashida Jones","77":"Daniel Day-Lewis,Pete Postlethwaite,Alison Crosbie","78":"Robert De Niro,Christopher Walken,John Cazale","79":"Ralph Fiennes,F. Murray Abraham,Mathieu Amalric","80":"Orson Welles,Joseph Cotten,Alida Valli","81":"Buster Keaton,Marion Mack,Glen Cavender","82":"Ben Affleck,Rosamund Pike,Neil Patrick Harris","83":"Victor Sj\u00c3\u00b6str\u00c3\u00b6m,Bibi Andersson,Ingrid Thulin","84":"Charlton Heston,Jack Hawkins,Stephen Boyd","85":"Daniel Radcliffe,Emma Watson,Rupert Grint","86":"Chiwetel Ejiofor,Michael Kenneth Williams,Michael Fassbender","87":"Ethan Hawke,Julie Delpy,Andrea Eckert","88":"Marlon Brando,Karl Malden,Lee J. Cobb","89":"Charles Chaplin,Mack Swain,Tom Murray","90":"Harrison Ford,Rutger Hauer,Sean Young","91":"Mohammad Amir Naji,Amir Farrokh Hashemian,Bahare Seddiqi","92":"Hilary Swank,Clint Eastwood,Morgan Freeman","93":"Leonardo DiCaprio,Tom Hanks,Christopher Walken","94":"Hitoshi Takagi,Noriko Hidaka,Chika Sakamoto","95":"Hugh Jackman,Jake Gyllenhaal,Viola Davis","96":"Clint Eastwood,Bee Vang,Christopher Carley","97":"William H. Macy,Frances McDormand,Steve Buscemi","98":"Tom Hardy,Nick Nolte,Joel Edgerton","99":"Ewan McGregor,Ewen Bremner,Jonny Lee Miller","100":"Frances McDormand,Woody Harrelson,Sam Rockwell","101":"William Holden,Alec Guinness,Jack Hawkins","102":"Chieko Baish\u00c3\u00b4,Takuya Kimura,Tatsuya Gash\u00c3\u00bbin","103":"Ricardo Dar\u00c3\u00adn,Soledad Villamil,Pablo Rago","104":"Ray Milland,Grace Kelly,Robert Cummings","105":"Jason Flemyng,Dexter Fletcher,Nick Moran","106":"Amy Poehler,Bill Hader,Lewis Black","107":"Hugo Weaving,Natalie Portman,Rupert Graves","108":"Clark Gable,Vivien Leigh,Thomas Mitchell","109":"Robert De Niro,Cathy Moriarty,Joe Pesci","110":"Jack Nicholson,Faye Dunaway,John Huston","111":"Anthony Hopkins,John Hurt,Anne Bancroft","112":"Kurt Russell,Wilford Brimley,Keith David","113":"Albert Brooks,Ellen DeGeneres,Alexander Gould","114":"Tommy Lee Jones,Javier Bardem,Josh Brolin","115":"Uma Thurman,David Carradine,Daryl Hannah","116":"Toshir\u00c3\u00b4 Mifune,Machiko Ky\u00c3\u00b4,Masayuki Mori","117":"Steve McQueen,James Garner,Richard Attenborough","118":"Sam Neill,Laura Dern,Jeff Goldblum","119":"Humphrey Bogart,Walter Huston,Tim Holt","120":"Graham Chapman,John Cleese,Eric Idle","121":"Tom Holland,Zendaya,Benedict Cumberbatch","122":"Toshir\u00c3\u00b4 Mifune,Eijir\u00c3\u00b4 T\u00c3\u00b4no,Tatsuya Nakadai","123":"Leonardo DiCaprio,Emily Mortimer,Mark Ruffalo","124":"Russell Crowe,Ed Harris,Jennifer Connelly","125":"Bruce Willis,Haley Joel Osment,Toni Collette","126":"Jim Carrey,Ed Harris,Laura Linney","127":"Daniel Day-Lewis,Paul Dano,Ciar\u00c3\u00a1n Hinds","128":"Clint Eastwood,Gene Hackman,Morgan Freeman","129":"Ivana Baquero,Ariadna Gil,Sergi L\u00c3\u00b3pez","130":"Robert De Niro,Sharon Stone,Joe Pesci","131":"Tatsuya Nakadai,Akira Terao,Jinpachi Nezu","132":"Spencer Tracy,Burt Lancaster,Richard Widmark","133":"Leonardo DiCaprio,Jonah Hill,Margot Robbie","134":"Viggo Mortensen,Mahershala Ali,Linda Cardellini","135":"Bette Davis,Anne Baxter,George Sanders","136":"Anthony Hopkins,Olivia Colman,Mark Gatiss","137":"Marilyn Monroe,Tony Curtis,Jack Lemmon","138":"Charles Chaplin,Edna Purviance,Jackie Coogan","139":"Christian Bale,Michael Caine,Ken Watanabe","140":"Aamir Khan,Sakshi Tanwar,Fatima Sana Shaikh","141":"Clint Eastwood,Lee Van Cleef,Gian Maria Volont\u00c3\u00a8","142":"Bruno Ganz,Alexandra Maria Lara,Ulrich Matthes","143":"Dean-Charles Chapman,George MacKay,Daniel Mays","144":"Darsheel Safary,Aamir Khan,Tisca Chopra","145":"Harrison Ford,Sean Connery,Alison Doody","146":"Lamberto Maggiorani,Enzo Staiola,Lianella Carell","147":"Jason Statham,Brad Pitt,Stephen Graham","148":"Bruce Willis,Alan Rickman,Bonnie Bedelia","149":"Kevin Spacey,Russell Crowe,Guy Pearce","150":"Brigitte Helm,Alfred Abel,Gustav Fr\u00c3\u00b6hlich","151":"Payman Maadi,Leila Hatami,Sareh Bayat","152":"Robert De Niro,Jodie Foster,Cybill Shepherd","153":"Al Pacino,Robert De Niro,Val Kilmer","154":"Edward Asner,Jordan Nagai,John Ratzenberger","155":"Lubna Azabal,M\u00c3\u00a9lissa D\u00c3\u00a9sormeaux-Poulin,Maxim Gaudette","156":"Paul Newman,Robert Redford,Robert Shaw","157":"Gregory Peck,John Megna,Frank Overton","158":"Al Pacino,Michelle Pfeiffer,Steven Bauer","159":"Lin-Manuel Miranda,Phillipa Soo,Leslie Odom Jr.","160":"Matthew Modine,R. Lee Ermey,Vincent D'Onofrio","161":"Fred MacMurray,Barbara Stanwyck,Edward G. Robinson","162":"Takashi Shimura,Nobuo Kaneko,Shin'ichi Himori","163":"Jack Lemmon,Shirley MacLaine,Fred MacMurray","164":"Malcolm McDowell,Patrick Magee,Michael Bates","165":"Audrey Tautou,Mathieu Kassovitz,Rufus","166":"James Stewart,Kim Novak,Barbara Bel Geddes","167":"Cary Grant,Eva Marie Saint,James Mason","168":"Peter O'Toole,Alec Guinness,Anthony Quinn","169":"Peter Lorre,Ellen Widmann,Inge Landgut","170":"Orson Welles,Joseph Cotten,Dorothy Comingore","171":"Aleksey Kravchenko,Olga Mironova,Liubomiras Laucevicius","172":"Mads Mikkelsen,Thomas Bo Larsen,Annika Wedderkopp","173":"Harvey Keitel,Tim Roth,Michael Madsen","174":"Jim Carrey,Kate Winslet,Tom Wilkinson","175":"Keir Dullea,Gary Lockwood,William Sylvester","176":"Zain Al Rafeea,Yordanos Shiferaw,Boluwatife Treasure Bankole","177":"Mark Hamill,Harrison Ford,Carrie Fisher","178":"Toshir\u00c3\u00b4 Mifune,Yutaka Sada,Tatsuya Nakadai","179":"Tom Hanks,Tim Allen,Joan Cusack","180":"Gene Kelly,Donald O'Connor,Debbie Reynolds","181":"Aamir Khan,Madhavan,Mona Singh","182":"Ellen Burstyn,Jared Leto,Jennifer Connelly","183":"Tom Cruise,Jennifer Connelly,Miles Teller","184":"Ry\u00c3\u00bbnosuke Kamiki,Mone Kamishiraishi,Ry\u00c3\u00b4 Narita","185":"Robin Williams,Matt Damon,Ben Affleck","186":"Robert De Niro,James Woods,Elizabeth McGovern","187":"Y\u00c3\u00b4ji Matsuda,Yuriko Ishida,Y\u00c3\u00bbko Tanaka","188":"Robert Downey Jr.,Chris Evans,Mark Ruffalo","189":"Mel Gibson,Sophie Marceau,Patrick McGoohan","190":"Tom Hanks,Tim Allen,Don Rickles","191":"Anthony Gonzalez,Gael Garc\u00c3\u00ada Bernal,Benjamin Bratt","192":"Joaquin Phoenix,Robert De Niro,Zazie Beetz","193":"Brad Pitt,Diane Kruger,Eli Roth","194":"F. Murray Abraham,Tom Hulce,Elizabeth Berridge","195":"Choi Min-sik,Yoo Ji-tae,Kang Hye-jeong","196":"Christian Bale,Tom Hardy,Anne Hathaway","197":"Peter Sellers,George C. Scott,Sterling Hayden","198":"Kevin Spacey,Annette Bening,Thora Birch","199":"Shameik Moore,Jake Johnson,Hailee Steinfeld","200":"Sigourney Weaver,Michael Biehn,Carrie Henn","201":"Tyrone Power,Marlene Dietrich,Charles Laughton","202":"Robert Downey Jr.,Chris Hemsworth,Mark Ruffalo","203":"Charles Chaplin,Paulette Goddard,Jack Oakie","204":"Jack Nicholson,Shelley Duvall,Danny Lloyd","205":"Kirk Douglas,Ralph Meeker,Adolphe Menjou","206":"William Holden,Gloria Swanson,Erich von Stroheim","207":"Ulrich M\u00c3\u00bche,Martina Gedeck,Sebastian Koch","208":"Ben Burtt,Elissa Knight,Jeff Garlin","209":"Jamie Foxx,Christoph Waltz,Leonardo DiCaprio","210":"Harrison Ford,Karen Allen,Paul Freeman","211":"Guy Pearce,Carrie-Anne Moss,Joe Pantoliano","212":"Martin Sheen,Marlon Brando,Robert Duvall","213":"Charles Chaplin,Virginia Cherrill,Florence Lee","214":"Sigourney Weaver,Tom Skerritt,John Hurt","215":"Philippe Noiret,Enzo Cannavale,Antonella Attili","216":"James Stewart,Grace Kelly,Wendell Corey","217":"Henry Fonda,Charles Bronson,Claudia Cardinale","218":"Charles Chaplin,Paulette Goddard,Henry Bergman","219":"Fran\u00c3\u00a7ois Cluzet,Omar Sy,Anne Le Ny","220":"Tsutomu Tatsumi,Ayano Shiraishi,Akemi Yamaguchi","221":"Tatsuya Nakadai,Akira Ishihama,Shima Iwashita","222":"Humphrey Bogart,Ingrid Bergman,Paul Henreid","223":"Miles Teller,J.K. Simmons,Melissa Benoist","224":"Christian Bale,Hugh Jackman,Scarlett Johansson","225":"Kevin Spacey,Gabriel Byrne,Chazz Palminteri","226":"Edward Norton,Edward Furlong,Beverly D'Angelo","227":"Leonardo DiCaprio,Matt Damon,Jack Nicholson","228":"Russell Crowe,Joaquin Phoenix,Connie Nielsen","229":"Matthew Broderick,Jeremy Irons,James Earl Jones","230":"Jean Reno,Gary Oldman,Natalie Portman","231":"Song Kang-ho,Lee Sun-kyun,Cho Yeo-jeong","232":"Adrien Brody,Thomas Kretschmann,Frank Finlay","233":"Anthony Perkins,Janet Leigh,Vera Miles","234":"Daveigh Chase,Suzanne Pleshette,Miyu Irino","235":"Michael J. Fox,Christopher Lloyd,Lea Thompson","236":"Arnold Schwarzenegger,Linda Hamilton,Edward Furlong","237":"Mark Hamill,Harrison Ford,Carrie Fisher","238":"Tom Hanks,Michael Clarke Duncan,David Morse","239":"Matthew McConaughey,Anne Hathaway,Jessica Chastain","240":"Roberto Benigni,Nicoletta Braschi,Giorgio Cantarini","241":"Tom Hanks,Matt Damon,Tom Sizemore","242":"Alexandre Rodrigues,Leandro Firmino,Matheus Nachtergaele","243":"Jodie Foster,Anthony Hopkins,Lawrence A. Bonney","244":"James Stewart,Donna Reed,Lionel Barrymore","245":"Toshir\u00c3\u00b4 Mifune,Takashi Shimura,Keiko Tsushima","246":"Morgan Freeman,Brad Pitt,Kevin Spacey","247":"Jack Nicholson,Louise Fletcher,Michael Berryman","248":"Robert De Niro,Ray Liotta,Joe Pesci"},"Public":{"0":"R","1":"R","2":"PG-13","3":"R","4":"Approved","5":"R","6":"PG-13","7":"R","8":"PG-13","9":"R","10":"PG-13","11":"R","12":"PG-13","13":"PG-13","14":"PG","15":"R","16":"PG","17":"PG-13","18":"PG","19":"G","20":"G","21":"R","22":"R","23":"G","24":"Not Rated","25":"Passed","26":"Not Rated","27":"Not Rated","28":"GP","29":"R","30":"Approved","31":"Not Rated","32":"Passed","33":"PG-13","34":"TV-MA","35":"Not Rated","36":"G","37":"Not Rated","38":"Passed","39":"PG","40":"Approved","41":"R","42":"PG","43":"R","44":"G","45":"R","46":"R","47":"Not Rated","48":"R","49":"G","50":"R","51":"R","52":"R","53":"R","54":"R","55":"PG","56":"PG-13","57":"PG-13","58":"Not Rated","59":"Passed","60":"PG","61":"PG","62":"R","63":"G","64":"PG","65":"Not Rated","66":"R","67":"R","68":"Not Rated","69":"R","70":"Not Rated","71":"Passed","72":"Passed","73":"R","74":"Not Rated","75":"PG","76":"PG","77":"R","78":"R","79":"R","80":"Approved","81":"Passed","82":"R","83":"Not Rated","84":"G","85":"PG-13","86":"R","87":"R","88":"Approved","89":"Passed","90":"R","91":"PG","92":"PG-13","93":"PG-13","94":"G","95":"R","96":"R","97":"R","98":"PG-13","99":"R","100":"R","101":"PG","102":"PG","103":"R","104":"PG","105":"R","106":"PG","107":"R","108":"Passed","109":"R","110":"R","111":"PG","112":"R","113":"G","114":"R","115":"R","116":"Not Rated","117":"Approved","118":"PG-13","119":"Passed","120":"PG","121":"PG-13","122":"Not Rated","123":"R","124":"PG-13","125":"PG-13","126":"PG","127":"R","128":"R","129":"R","130":"R","131":"R","132":"Approved","133":"R","134":"PG-13","135":"Passed","136":"PG-13","137":"Passed","138":"Passed","139":"PG-13","140":"Not Rated","141":"R","142":"R","143":"R","144":"PG","145":"PG-13","146":"Not Rated","147":"R","148":"R","149":"R","150":"Not Rated","151":"PG-13","152":"R","153":"R","154":"PG","155":"R","156":"PG","157":"Approved","158":"R","159":"PG-13","160":"R","161":"Passed","162":"Not Rated","163":"Approved","164":"X","165":"R","166":"PG","167":"Approved","168":"Approved","169":"Passed","170":"PG","171":"Not Rated","172":"R","173":"R","174":"R","175":"G","176":"R","177":"PG","178":"Not Rated","179":"G","180":"G","181":"PG-13","182":"Unrated","183":"PG-13","184":"TV-PG","185":"R","186":"R","187":"PG-13","188":"PG-13","189":"R","190":"G","191":"PG","192":"R","193":"R","194":"PG","195":"R","196":"PG-13","197":"PG","198":"R","199":"PG","200":"R","201":"Approved","202":"PG-13","203":"G","204":"R","205":"Approved","206":"Passed","207":"R","208":"G","209":"R","210":"PG","211":"R","212":"R","213":"G","214":"R","215":"PG","216":"PG","217":"PG-13","218":"G","219":"R","220":"Not Rated","221":"Not Rated","222":"PG","223":"R","224":"PG-13","225":"R","226":"R","227":"R","228":"R","229":"G","230":"R","231":"R","232":"R","233":"R","234":"PG","235":"PG","236":"R","237":"PG","238":"R","239":"PG-13","240":"PG-13","241":"R","242":"R","243":"R","244":"PG","245":"Not Rated","246":"R","247":"R","248":"R"}}